ProcessingFramework/AppFramework.py
ProcessingFramework/__init__.py
Processing_Framework_py-0.0.2.dist-info/METADATA
Processing_Framework_py-0.0.2.dist-info/WHEEL
Processing_Framework_py-0.0.2.dist-info/top_level.txt
Processing_Framework_py-0.0.2.dist-info/RECORD
